{"_path":"/posts/code-log/code-log-day-0","_dir":"code-log","_draft":false,"_partial":false,"_locale":"","title":"Code Log - Day 0","description":"Planning the Code Log","head":{"meta":[{"name":"author","content":"Caio Prado"},{"name":"keywords","content":"challenge"}]},"publishedAt":"2025-01-06T08:00:00.000Z","tags":"challenge,daily-coding","collections":"Code Log","toc":true,"body":{"type":"root","children":[{"type":"element","tag":"h1","props":{"id":""},"children":[{"type":"element","tag":"binding","props":{"value":"$doc.title"},"children":[]}]},{"type":"element","tag":"h2","props":{"id":"the-challenge"},"children":[{"type":"text","value":"The Challenge"}]},{"type":"element","tag":"p","props":{},"children":[{"type":"text","value":"It consists in daily coding practice, where i'm going to dedicate part of my day do produce programming related stuff, like solving some code online judges exercises or working on a side project."}]},{"type":"element","tag":"h2","props":{"id":"in-practice"},"children":[{"type":"text","value":"In Practice"}]},{"type":"element","tag":"p","props":{},"children":[{"type":"text","value":"To start, i'll be doing LeetCode exercises and working on some unfinished projects:"}]},{"type":"element","tag":"ul","props":{},"children":[{"type":"element","tag":"li","props":{},"children":[{"type":"element","tag":"a","props":{"href":"https://github.com/caioopr/second_brain","rel":["nofollow"]},"children":[{"type":"text","value":"Second Brain"}]}]},{"type":"element","tag":"li","props":{},"children":[{"type":"element","tag":"a","props":{"href":"https://github.com/caioopr/ixtore","rel":["nofollow"]},"children":[{"type":"text","value":"Ixtore"}]}]},{"type":"element","tag":"li","props":{},"children":[{"type":"element","tag":"a","props":{"href":"https://github.com/caioopr/productivist_ecosystem","rel":["nofollow"]},"children":[{"type":"text","value":"Productivist Ecosystem"}]}]},{"type":"element","tag":"li","props":{},"children":[{"type":"element","tag":"a","props":{"href":"https://github.com/caioopr/library_management_systems","rel":["nofollow"]},"children":[{"type":"text","value":"Library Management System"}]}]},{"type":"element","tag":"li","props":{},"children":[{"type":"element","tag":"a","props":{"href":"https://github.com/caioopr/Miahbits","rel":["nofollow"]},"children":[{"type":"text","value":"Miahbits"}]}]}]},{"type":"element","tag":"p","props":{},"children":[{"type":"text","value":"After these, if i'm still unemployed, i'll be focusing on writing data structures/algorithms and design patterns implementations, and starting new projects."}]}],"toc":{"title":"","searchDepth":2,"depth":2,"links":[{"id":"the-challenge","depth":2,"text":"The Challenge"},{"id":"in-practice","depth":2,"text":"In Practice"}]}},"_type":"markdown","_id":"content:posts:Code Log:Code Log - Day 0.md","_source":"content","_file":"posts/Code Log/Code Log - Day 0.md","_extension":"md"}