{"generatedAt":1736296949089,"generateTime":205,"contents":[{"_path":"/about","_dir":"","_draft":false,"_partial":false,"_locale":"","title":"Hi there, i'm Caio 👋","description":"","body":{"type":"root","children":[{"type":"element","tag":"h1","props":{"id":"hi-there-im-caio"},"children":[{"type":"text","value":"Hi there, i'm Caio 👋"}]},{"type":"element","tag":"ul","props":{},"children":[{"type":"element","tag":"li","props":{},"children":[{"type":"text","value":"📝 This is the place where you will find some of my study notes and tutorials"}]},{"type":"element","tag":"li","props":{},"children":[{"type":"text","value":"👨‍🎓 I’m currently majoring in Computer Science"}]},{"type":"element","tag":"li","props":{},"children":[{"type":"text","value":"📈 Improving my back-end skills"}]},{"type":"element","tag":"li","props":{},"children":[{"type":"text","value":"🔋 Current stack: Spring Boot | Go | Vue.js | Nuxt.js"}]},{"type":"element","tag":"li","props":{},"children":[{"type":"text","value":"🧑‍💻 Working on side projects"}]},{"type":"element","tag":"li","props":{},"children":[{"type":"text","value":"📫 Email me: "},{"type":"element","tag":"a","props":{"href":"mailto:caioppubli@gmail.com"},"children":[{"type":"text","value":"caioppubli@gmail.com"}]}]}]}],"toc":{"title":"","searchDepth":2,"depth":2,"links":[]}},"_type":"markdown","_id":"content:about.md","_source":"content","_file":"about.md","_extension":"md"},{"_path":"/collections","_dir":"","_draft":false,"_partial":false,"_locale":"","title":"","description":"","body":{"type":"root","children":[{"type":"element","tag":"filter-posts","props":{},"children":[]},{"type":"element","tag":"blog-posts","props":{":tags-on":"true"},"children":[]}],"toc":{"title":"","searchDepth":2,"depth":2,"links":[]}},"_type":"markdown","_id":"content:collections:index.md","_source":"content","_file":"collections/index.md","_extension":"md"},{"_path":"/","_dir":"","_draft":false,"_partial":false,"_locale":"","title":"Latest Posts","description":"","body":{"type":"root","children":[{"type":"element","tag":"h1","props":{"id":"latest-posts"},"children":[{"type":"text","value":"Latest Posts"}]},{"type":"element","tag":"blog-posts","props":{":limit":"5",":tags-on":"false"},"children":[]}],"toc":{"title":"","searchDepth":2,"depth":2,"links":[]}},"_type":"markdown","_id":"content:index.md","_source":"content","_file":"index.md","_extension":"md"},{"_path":"/posts/coding-every-day-until-i-get-a-job-day-0","_dir":"posts","_draft":false,"_partial":false,"_locale":"","title":"Coding Every Day Until I Get a Job - Day 0","description":"Planning the Coding Every Day Challenge","head":{"meta":[{"name":"author","content":"Caio Prado"},{"name":"keywords","content":"challenge"}]},"publishedAt":"2025-01-06T08:00:00.000Z","tags":"challenge, daily-coding ","toc":true,"body":{"type":"root","children":[{"type":"element","tag":"h1","props":{"id":""},"children":[{"type":"element","tag":"binding","props":{"value":"$doc.title"},"children":[]}]},{"type":"element","tag":"h2","props":{"id":"the-challenge"},"children":[{"type":"text","value":"The Challenge"}]},{"type":"element","tag":"p","props":{},"children":[{"type":"text","value":"The challenge consists in daily coding practice, where i'm going to dedicate part of my day do produce programming related stuff, like solving some code online judges exercises or working on a side project. Of course, everything while searching for job."}]},{"type":"element","tag":"h2","props":{"id":"in-practice"},"children":[{"type":"text","value":"In Practice"}]},{"type":"element","tag":"p","props":{},"children":[{"type":"text","value":"To start, i'll be doing LeetCode exercises and working on some unfinished projects:"}]},{"type":"element","tag":"ul","props":{},"children":[{"type":"element","tag":"li","props":{},"children":[{"type":"element","tag":"a","props":{"href":"https://github.com/caioopr/second_brain","rel":["nofollow"]},"children":[{"type":"text","value":"Second Brain"}]}]},{"type":"element","tag":"li","props":{},"children":[{"type":"element","tag":"a","props":{"href":"https://github.com/caioopr/ixtore","rel":["nofollow"]},"children":[{"type":"text","value":"Ixtore"}]}]},{"type":"element","tag":"li","props":{},"children":[{"type":"element","tag":"a","props":{"href":"https://github.com/caioopr/productivist_ecosystem","rel":["nofollow"]},"children":[{"type":"text","value":"Productivist Ecosystem"}]}]},{"type":"element","tag":"li","props":{},"children":[{"type":"element","tag":"a","props":{"href":"https://github.com/caioopr/library_management_systems","rel":["nofollow"]},"children":[{"type":"text","value":"Library Management System"}]}]},{"type":"element","tag":"li","props":{},"children":[{"type":"element","tag":"a","props":{"href":"https://github.com/caioopr/Miahbits","rel":["nofollow"]},"children":[{"type":"text","value":"Miahbits"}]}]}]},{"type":"element","tag":"p","props":{},"children":[{"type":"text","value":"After these, if i'm still unemployed, i'll be focusing on writing data structures/algorithms and design patterns implementations, and starting new projects."}]}],"toc":{"title":"","searchDepth":2,"depth":2,"links":[{"id":"the-challenge","depth":2,"text":"The Challenge"},{"id":"in-practice","depth":2,"text":"In Practice"}]}},"_type":"markdown","_id":"content:posts:Coding Every Day Until I Get a Job - Day 0.md","_source":"content","_file":"posts/Coding Every Day Until I Get a Job - Day 0.md","_extension":"md"},{"_path":"/posts","_dir":"","_draft":false,"_partial":false,"_locale":"","title":"","description":"","body":{"type":"root","children":[{"type":"element","tag":"filter-posts","props":{},"children":[]},{"type":"element","tag":"blog-posts","props":{":tags-on":"true"},"children":[]}],"toc":{"title":"","searchDepth":2,"depth":2,"links":[]}},"_type":"markdown","_id":"content:posts:index.md","_source":"content","_file":"posts/index.md","_extension":"md"},{"_path":"/projects","_dir":"","_draft":false,"_partial":false,"_locale":"","title":"","description":"","body":{"type":"root","children":[{"type":"element","tag":"projects-list","props":{},"children":[]}],"toc":{"title":"","searchDepth":2,"depth":2,"links":[]}},"_type":"markdown","_id":"content:projects:index.md","_source":"content","_file":"projects/index.md","_extension":"md"},{"_path":"/projects/ixtore","_dir":"projects","_draft":false,"_partial":false,"_locale":"","title":"Ixtore Web Application","description":"A Sales and Customers Management System","head":{"meta":[{"name":"author","content":"Caio Prado"},{"name":"keywords","content":"challenge"}]},"publishedAt":"2025-01-06T08:00:00.000Z","tags":"vue.js,pinia,tailwindcss,java,spring boot,docker,web app,full-stack","toc":true,"body":{"type":"root","children":[{"type":"element","tag":"h1","props":{"id":""},"children":[{"type":"element","tag":"binding","props":{"value":"$doc.title"},"children":[]}]},{"type":"element","tag":"p","props":{},"children":[{"type":"element","tag":"strong","props":{},"children":[{"type":"element","tag":"binding","props":{"value":"$doc.description"},"children":[]}]}]},{"type":"element","tag":"h2","props":{"id":"introduction"},"children":[{"type":"text","value":"Introduction"}]},{"type":"element","tag":"p","props":{},"children":[{"type":"text","value":"The "},{"type":"element","tag":"a","props":{"href":"https://github.com/caioopr/ixtore","rel":["nofollow"]},"children":[{"type":"text","value":"Ixtore"}]},{"type":"text","value":" ixtore is a sales and customers management system developed with Vue.js, Pinia and TailwindCSS for the front-end and Spring Boot for the back-end, both dockerized for better developer experience and easier deployment."}]}],"toc":{"title":"","searchDepth":2,"depth":2,"links":[{"id":"introduction","depth":2,"text":"Introduction"}]}},"_type":"markdown","_id":"content:projects:Ixtore.md","_source":"content","_file":"projects/Ixtore.md","_extension":"md"}],"navigation":[{"title":"Hi there, i'm Caio 👋","_path":"/about"},{"title":"","_path":"/collections","children":[{"title":"","_path":"/collections"}]},{"title":"Latest Posts","_path":"/"},{"title":"","_path":"/posts","children":[{"title":"Coding Every Day Until I Get a Job - Day 0","_path":"/posts/coding-every-day-until-i-get-a-job-day-0"},{"title":"","_path":"/posts"}]},{"title":"","_path":"/projects","children":[{"title":"","_path":"/projects"},{"title":"Ixtore Web Application","_path":"/projects/ixtore"}]}]}